mylib029/__init__.py
mylib029-0.1.dist-info/LICENSE.txt
mylib029-0.1.dist-info/METADATA
mylib029-0.1.dist-info/WHEEL
mylib029-0.1.dist-info/top_level.txt
mylib029-0.1.dist-info/RECORD
